LICENSE_GPL2.0.txt
LICENSE_LGPL_2.1.txt
MANIFEST.in
README.md
setup.py
django_diazo/__init__.py
django_diazo/admin.py
django_diazo/apps.py
django_diazo/context_processors.py
django_diazo/middleware.py
django_diazo/models.py
django_diazo/settings.py
django_diazo/theme.py
django_diazo/wsgi.py
django_diazo.egg-info/PKG-INFO
django_diazo.egg-info/SOURCES.txt
django_diazo.egg-info/dependency_links.txt
django_diazo.egg-info/not-zip-safe
django_diazo.egg-info/pbr.json
django_diazo.egg-info/requires.txt
django_diazo.egg-info/top_level.txt
django_diazo/contrib/__init__.py
django_diazo/contrib/cms/__init__.py
django_diazo/contrib/cms/apps.py
django_diazo/contrib/cms/cms_toolbar.py
django_diazo/contrib/cms/middleware.py
django_diazo/contrib/cms/templates/cms/toolbar/items/on_off.html
django_diazo/contrib/themes/__init__.py
django_diazo/contrib/themes/blue/__init__.py
django_diazo/contrib/themes/blue/diazo.py
django_diazo/contrib/themes/blue/static/blue/rules.xml
django_diazo/contrib/themes/django_bootstrap/__init__.py
django_diazo/contrib/themes/django_bootstrap/diazo.py
django_diazo/contrib/themes/django_bootstrap/static/django_bootstrap/index.html
django_diazo/contrib/themes/django_bootstrap/static/django_bootstrap/login.html
django_diazo/contrib/themes/django_bootstrap/static/django_bootstrap/login.xml
django_diazo/contrib/themes/django_bootstrap/static/django_bootstrap/rules.xml
django_diazo/contrib/themes/django_bootstrap/static/django_bootstrap/assets/css/docs.css
django_diazo/contrib/themes/django_bootstrap/static/django_bootstrap/assets/css/pygments-manni.css
django_diazo/contrib/themes/django_bootstrap/static/django_bootstrap/assets/css/signin.css
django_diazo/contrib/themes/django_bootstrap/static/django_bootstrap/assets/ico/apple-touch-icon-114-precomposed.png
django_diazo/contrib/themes/django_bootstrap/static/django_bootstrap/assets/ico/apple-touch-icon-144-precomposed.png
django_diazo/contrib/themes/django_bootstrap/static/django_bootstrap/assets/ico/apple-touch-icon-57-precomposed.png
django_diazo/contrib/themes/django_bootstrap/static/django_bootstrap/assets/ico/apple-touch-icon-72-precomposed.png
django_diazo/contrib/themes/django_bootstrap/static/django_bootstrap/assets/ico/favicon.png
