Metadata-Version: 1.1
Name: django-diazo
Version: 2.0.1
Summary: Integrate Diazo in Django using WSGI middleware and
Home-page: https://github.com/Goldmund-Wyldebeast-Wunderliebe/django-diazo
Author: Douwe van der Meij, Job Ganzevoort
Author-email: vandermeij@gw20e.com
License: UNKNOWN
Platform: UNKNOWN
Classifier: Development Status :: 4 - Beta
Classifier: Environment :: Web Environment
Classifier: Intended Audience :: Developers
Classifier: License :: OSI Approved :: GNU General Public License v2 (GPLv2)
Classifier: License :: OSI Approved :: GNU Lesser General Public License v2 or later (LGPLv2+)
Classifier: Operating System :: OS Independent
Classifier: Programming Language :: Python
Classifier: Framework :: Django
